p81api/__init__.py
p81api/api.py
p81api/model.py
p81api-0.8.dist-info/METADATA
p81api-0.8.dist-info/WHEEL
p81api-0.8.dist-info/top_level.txt
p81api-0.8.dist-info/RECORD
