Metadata-Version: 2.1
Name: p81api
Version: 0.8
Summary: A thin python wrapper of Perimeter81 public API
Home-page: https://github.com/vladbekker-p81/perimeter81-api
Author: Avishay Balderman
Author-email: avishay.balderman@perimeter81.com
License: UNKNOWN
Platform: UNKNOWN
Classifier: Programming Language :: Python :: 3
Classifier: License :: OSI Approved :: MIT License
Classifier: Operating System :: OS Independent
Requires-Python: >=3.7
